bq_fake_pii_table_creator/__init__.py
bq_fake_pii_table_creator/bq_creator.py
bq_fake_pii_table_creator/bq_fake_table_creator.py
bq_fake_pii_table_creator/bq_fake_table_creator_cli.py
bq_fake_pii_table_creator/csv_creator.py
bq_fake_pii_table_creator/dataframe_creator.py
bq_fake_pii_table_creator/gcs_storage_client_helper.py
bq_fake_pii_table_creator/uuid_helper.py
bq_fake_pii_table_creator-0.0.4.dist-info/LICENSE
bq_fake_pii_table_creator-0.0.4.dist-info/METADATA
bq_fake_pii_table_creator-0.0.4.dist-info/WHEEL
bq_fake_pii_table_creator-0.0.4.dist-info/entry_points.txt
bq_fake_pii_table_creator-0.0.4.dist-info/top_level.txt
bq_fake_pii_table_creator-0.0.4.dist-info/RECORD
