Metadata-Version: 2.1
Name: bq-fake-pii-table-creator
Version: 0.0.4
Summary: Library for creating BQ tables with fake sensible data
Home-page: UNKNOWN
Author: Marcelo Costa
Author-email: mesmacosta@gmail.com
License: UNKNOWN
Platform: Posix; MacOS X; Windows
Classifier: Development Status :: 3 - Alpha
Classifier: Natural Language :: English
Classifier: Programming Language :: Python
Classifier: Programming Language :: Python :: 3.6
Classifier: Programming Language :: Python :: 3.7
Requires-Dist: pandas
Requires-Dist: faker
Requires-Dist: google-cloud-bigquery
Requires-Dist: google-cloud-storage
